CalculusWithApplicationsMit18013a/README.md
CalculusWithApplicationsMit18013a/__init__.py
CalculusWithApplicationsMit18013a/__main__.py
CalculusWithApplicationsMit18013a/file.epub
CalculusWithApplicationsMit18013a/index.html
CalculusWithApplicationsMit18013a/css/__init__.py
CalculusWithApplicationsMit18013a/css/annotations.css
CalculusWithApplicationsMit18013a/css/main.css
CalculusWithApplicationsMit18013a/css/normalize.css
CalculusWithApplicationsMit18013a/css/popup.css
CalculusWithApplicationsMit18013a/font/__init__.py
CalculusWithApplicationsMit18013a/font/fontello.eot
CalculusWithApplicationsMit18013a/font/fontello.svg
CalculusWithApplicationsMit18013a/font/fontello.ttf
CalculusWithApplicationsMit18013a/font/fontello.woff
CalculusWithApplicationsMit18013a/img/__init__.py
CalculusWithApplicationsMit18013a/img/annotator-glyph-sprite.png
CalculusWithApplicationsMit18013a/img/annotator-icon-sprite.png
CalculusWithApplicationsMit18013a/img/apple-touch-icon.png
CalculusWithApplicationsMit18013a/img/cancelfullscreen.png
CalculusWithApplicationsMit18013a/img/close.png
CalculusWithApplicationsMit18013a/img/fullscreen.png
CalculusWithApplicationsMit18013a/img/loader.gif
CalculusWithApplicationsMit18013a/img/menu-icon.png
CalculusWithApplicationsMit18013a/img/save.png
CalculusWithApplicationsMit18013a/img/saved.png
CalculusWithApplicationsMit18013a/img/settings-s.png
CalculusWithApplicationsMit18013a/img/settings.png
CalculusWithApplicationsMit18013a/img/star.png
CalculusWithApplicationsMit18013a/js/__init__.py
CalculusWithApplicationsMit18013a/js/epub.js
CalculusWithApplicationsMit18013a/js/epub.min.js
CalculusWithApplicationsMit18013a/js/epub.min.map
CalculusWithApplicationsMit18013a/js/hooks.min.js
CalculusWithApplicationsMit18013a/js/hooks.min.map
CalculusWithApplicationsMit18013a/js/reader.js
CalculusWithApplicationsMit18013a/js/reader.js.map
CalculusWithApplicationsMit18013a/js/reader.min.js
CalculusWithApplicationsMit18013a/js/reader.min.map
calculus_with_applications_mit_18_013a-2024.3.2.0.dist-info/METADATA
calculus_with_applications_mit_18_013a-2024.3.2.0.dist-info/WHEEL
calculus_with_applications_mit_18_013a-2024.3.2.0.dist-info/entry_points.txt
calculus_with_applications_mit_18_013a-2024.3.2.0.dist-info/top_level.txt
calculus_with_applications_mit_18_013a-2024.3.2.0.dist-info/RECORD
